dbaas_k8s_client-0.1.0.dist-info/RECORD
dbaas_k8s_client-0.1.0.dist-info/metadata.json
dbaas_k8s_client-0.1.0.dist-info/WHEEL
dbaas_k8s_client-0.1.0.dist-info/DESCRIPTION.rst
dbaas_k8s_client-0.1.0.dist-info/top_level.txt
dbaas_k8s_client-0.1.0.dist-info/METADATA
k8s_client/client.py
k8s_client/__init__.py
