Metadata-Version: 2.0
Name: dbaas-k8s-client
Version: 0.1.0
Summary: Client for k8s
Home-page: https://github.com/globocom/dbaas-k8s-client
Author: dbaas
Author-email: dbaas@g.globo
License: BSD
Keywords: k8s_client,kubernetes,python
Platform: UNKNOWN
Classifier: Development Status :: 2 - Pre-Alpha
Classifier: Intended Audience :: Developers
Classifier: License :: OSI Approved :: BSD License
Classifier: Natural Language :: English
Classifier: Programming Language :: Python :: 2
Classifier: Programming Language :: Python :: 2.6
Classifier: Programming Language :: Python :: 2.7
Classifier: Programming Language :: Python :: 3
Classifier: Programming Language :: Python :: 3.3
Classifier: Programming Language :: Python :: 3.4
Requires-Dist: kubernetes (==11.0.0)
